test_github_actions/__init__.py
test_github_actions/file.py
test_github_actions/harmonic_mean.pyx
test_github_actions-0.1.1.dist-info/METADATA
test_github_actions-0.1.1.dist-info/WHEEL
test_github_actions-0.1.1.dist-info/RECORD
